scipy/HACKING.rst.txt
scipy/INSTALL.rst.txt
scipy/LICENSE.txt
scipy/LICENSES_bundled.txt
scipy/THANKS.txt
scipy/__config__.py
scipy/__init__.py
scipy/_distributor_init.py
scipy/conftest.py
scipy/linalg.pxd
scipy/optimize.pxd
scipy/setup.py
scipy/special.pxd
scipy/version.py
scipy/_build_utils/__init__.py
scipy/_build_utils/_fortran.py
scipy/_build_utils/compiler_helper.py
scipy/_build_utils/setup.py
scipy/_build_utils/system_info.py
scipy/_build_utils/tests/__init__.py
scipy/_build_utils/tests/test_circular_imports.py
scipy/_build_utils/tests/test_scipy_version.py
scipy/_lib/__init__.py
scipy/_lib/_ccallback.py
scipy/_lib/_ccallback_c.cpython-37m-aarch64-linux-gnu.so
scipy/_lib/_fpumode.cpython-37m-aarch64-linux-gnu.so
scipy/_lib/_gcutils.py
scipy/_lib/_numpy_compat.py
scipy/_lib/_pep440.py
scipy/_lib/_test_ccallback.cpython-37m-aarch64-linux-gnu.so
scipy/_lib/_testutils.py
scipy/_lib/_threadsafety.py
scipy/_lib/_tmpdirs.py
scipy/_lib/_util.py
scipy/_lib/_version.py
scipy/_lib/decorator.py
scipy/_lib/deprecation.py
scipy/_lib/doccer.py
scipy/_lib/messagestream.cpython-37m-aarch64-linux-gnu.so
scipy/_lib/setup.py
scipy/_lib/six.py
scipy/_lib/uarray.py
scipy/_lib/_uarray/LICENSE
scipy/_lib/_uarray/__init__.py
scipy/_lib/_uarray/_backend.py
scipy/_lib/_uarray/_uarray.cpython-37m-aarch64-linux-gnu.so
scipy/_lib/_uarray/setup.py
scipy/_lib/tests/__init__.py
scipy/_lib/tests/test__gcutils.py
scipy/_lib/tests/test__testutils.py
scipy/_lib/tests/test__threadsafety.py
scipy/_lib/tests/test__util.py
scipy/_lib/tests/test__version.py
scipy/_lib/tests/test_ccallback.py
scipy/_lib/tests/test_import_cycles.py
scipy/_lib/tests/test_tmpdirs.py
scipy/_lib/tests/test_warnings.py
scipy/cluster/__init__.py
scipy/cluster/_hierarchy.cpython-37m-aarch64-linux-gnu.so
scipy/cluster/_optimal_leaf_ordering.cpython-37m-aarch64-linux-gnu.so
scipy/cluster/_vq.cpython-37m-aarch64-linux-gnu.so
scipy/cluster/hierarchy.py
scipy/cluster/setup.py
scipy/cluster/vq.py
scipy/cluster/tests/__init__.py
scipy_mpmkp-1.4.1.dist-info/LICENSE.txt
scipy_mpmkp-1.4.1.dist-info/LICENSES_bundled.txt
scipy_mpmkp-1.4.1.dist-info/METADATA
scipy_mpmkp-1.4.1.dist-info/WHEEL
scipy_mpmkp-1.4.1.dist-info/top_level.txt
scipy_mpmkp-1.4.1.dist-info/RECORD
