Metadata-Version: 2.1
Name: scipy-mpmkp
Version: 1.4.1
Summary: SciPy: Scientific Library for Python
Home-page: https://www.scipy.org
Maintainer: SciPy Developers
Maintainer-email: scipy-dev@python.org
License: BSD
Download-URL: https://github.com/scipy/scipy/releases
Project-URL: Bug Tracker, https://github.com/scipy/scipy/issues
Project-URL: Documentation, https://docs.scipy.org/doc/scipy/reference/
Project-URL: Source Code, https://github.com/scipy/scipy
Platform: Windows
Platform: Linux
Platform: Solaris
Platform: Mac OS-X
Platform: Unix
Classifier: Development Status :: 5 - Production/Stable
Classifier: Intended Audience :: Science/Research
Classifier: Intended Audience :: Developers
Classifier: License :: OSI Approved :: BSD License
Classifier: Programming Language :: C
Classifier: Programming Language :: Python
Classifier: Programming Language :: Python :: 3
Classifier: Programming Language :: Python :: 3.5
Classifier: Programming Language :: Python :: 3.6
Classifier: Programming Language :: Python :: 3.7
Classifier: Topic :: Software Development
Classifier: Topic :: Scientific/Engineering
Classifier: Operating System :: Microsoft :: Windows
Classifier: Operating System :: POSIX
Classifier: Operating System :: Unix
Classifier: Operating System :: MacOS
Requires-Python: >=3.5
Requires-Dist: numpy (>=1.13.3)
